sarw_spheres.cpython-310-x86_64-linux-gnu.so
sarw_spheres-0.0.9.dist-info/METADATA
sarw_spheres-0.0.9.dist-info/WHEEL
sarw_spheres-0.0.9.dist-info/top_level.txt
sarw_spheres-0.0.9.dist-info/RECORD
sarw_spheres-0.0.9.dist-info/licenses/LICENSE
