Metadata-Version: 2.4
Name: sarw_spheres
Version: 0.0.9
Summary: Generate self-avoiding random walks (SARW) for spheres of given sizes.
Home-page: https://github.com/RadostW/sarw_spheres
Author: Radost Waszkiewicz
Author-email: radost.waszkiewicz@gmail.com
License: MIT
Project-URL: Documentation, https://github.com/RadostW/sarw_spheres
Project-URL: Source, https://github.com/RadostW/sarw_spheres
License-File: LICENSE
Requires-Dist: numpy>=2.0
Dynamic: author
Dynamic: author-email
Dynamic: description
Dynamic: description-content-type
Dynamic: home-page
Dynamic: license
Dynamic: license-file
Dynamic: project-url
Dynamic: requires-dist
Dynamic: summary
